scrapy_qiniu/__init__.py
scrapy_qiniu/impl.py
scrapy_qiniu-0.1.2.dist-info/DESCRIPTION.rst
scrapy_qiniu-0.1.2.dist-info/METADATA
scrapy_qiniu-0.1.2.dist-info/metadata.json
scrapy_qiniu-0.1.2.dist-info/RECORD
scrapy_qiniu-0.1.2.dist-info/top_level.txt
scrapy_qiniu-0.1.2.dist-info/WHEEL
