Metadata-Version: 2.0
Name: scrapy-qiniu
Version: 0.1.2
Summary: Scrapy pipeline extension for qiniu.com
Home-page: https://github.com/haizi-zh/scrapy-qiniu
Author: Zephyre
Author-email: haizi.zh@gmail.com
License: MIT
Keywords: crawler,spider,scrapy,qiniu
Platform: UNKNOWN
Classifier: Intended Audience :: Developers
Classifier: License :: OSI Approved :: MIT License
Classifier: Operating System :: OS Independent
Classifier: Natural Language :: Chinese (Simplified)
Classifier: Natural Language :: Chinese (Traditional)
Classifier: Programming Language :: Python
Classifier: Programming Language :: Python :: 2
Classifier: Programming Language :: Python :: 2.7
Classifier: Framework :: Scrapy
Classifier: Topic :: Internet :: WWW/HTTP
Classifier: Topic :: Software Development :: Libraries :: Application Frameworks
Classifier: Topic :: Software Development :: Libraries :: Python Modules
Classifier: Environment :: Console
Requires-Dist: Scrapy
Requires-Dist: qiniu
